grpc_addon.py
gen/buf/validate/validate_pb2.py
gen/mitmproxygrpc/v1/service_connect.py
gen/mitmproxygrpc/v1/service_pb2.py
mitmproxy_addon_grpc-0.1.0.dist-info/licenses/LICENSE
mitmproxy_addon_grpc-0.1.0.dist-info/METADATA
mitmproxy_addon_grpc-0.1.0.dist-info/WHEEL
mitmproxy_addon_grpc-0.1.0.dist-info/top_level.txt
mitmproxy_addon_grpc-0.1.0.dist-info/RECORD
