Metadata-Version: 2.4
Name: mitmproxy_addon_grpc
Version: 0.1.0
Requires-Python: >=3.12
License-File: LICENSE
Requires-Dist: connect-python
Requires-Dist: protobuf>=6.33.1
Requires-Dist: mitmproxy>=12.2.0
Dynamic: license-file
